zdict/__init__.py
zdict/__main__.py
zdict/api.py
zdict/completer.py
zdict/constants.py
zdict/dictionary.py
zdict/easter_eggs.py
zdict/exceptions.py
zdict/loader.py
zdict/models.py
zdict/utils.py
zdict/zdict.py
zdict/dictionaries/__init__.py
zdict/dictionaries/itaigi.py
zdict/dictionaries/jisho.py
zdict/dictionaries/moe.py
zdict/dictionaries/naer.py
zdict/dictionaries/oxford.py
zdict/dictionaries/spanish.py
zdict/dictionaries/template.py
zdict/dictionaries/urban.py
zdict/dictionaries/wiktionary.py
zdict/dictionaries/yahoo.py
zdict/dictionaries/yandex.py
zdict/tests/__init__.py
zdict/tests/test_api.py
zdict/tests/test_arguments.py
zdict/tests/test_completer.py
zdict/tests/test_easter_eggs.py
zdict/tests/test_loader.py
zdict/tests/test_utils.py
zdict/tests/dictionaries/__init__.py
zdict/tests/dictionaries/test_itaigi.py
zdict/tests/dictionaries/test_jisho.py
zdict/tests/dictionaries/test_moe.py
zdict/tests/dictionaries/test_naer.py
zdict/tests/dictionaries/test_oxford.py
zdict/tests/dictionaries/test_spanish.py
zdict/tests/dictionaries/test_template.py
zdict/tests/dictionaries/test_urban.py
zdict/tests/dictionaries/test_wiktionary.py
zdict/tests/dictionaries/test_yahoo.py
zdict/tests/dictionaries/test_yandex.py
zdict-5.0.1.data/scripts/zdict
zdict-5.0.1.dist-info/LICENSE.md
zdict-5.0.1.dist-info/METADATA
zdict-5.0.1.dist-info/WHEEL
zdict-5.0.1.dist-info/top_level.txt
zdict-5.0.1.dist-info/RECORD
