Metadata-Version: 2.1
Name: zdict
Version: 5.0.1
Summary: The last online dictionary framework you need. (?)
Home-page: https://github.com/zdict/zdict
Author: Frank Zheng
Author-email: github@m157q.tw
Maintainer: Frank Zheng, Iblis Lin, Chang-Yen Chih, Chiu-Hsiang Hsu
Maintainer-email: github@m157q.tw,e196819@hotmail.com,michael66230@gmail.com,wdv4758h@gmail.com
License: GPL3
Download-URL: https://github.com/zdict/zdict/archive/v5.0.1.zip
Keywords: cli,dictionary,framework
Platform: Linux
Platform: Mac
Classifier: Development Status :: 5 - Production/Stable
Classifier: Environment :: Console
Classifier: Intended Audience :: End Users/Desktop
Classifier: License :: OSI Approved :: GNU General Public License v3 (GPLv3)
Classifier: Natural Language :: Chinese (Traditional)
Classifier: Natural Language :: English
Classifier: Operating System :: POSIX :: Linux
Classifier: Operating System :: MacOS :: MacOS X
Classifier: Programming Language :: Python :: 3 :: Only
Classifier: Programming Language :: Python :: 3.7
Classifier: Programming Language :: Python :: 3.8
Classifier: Programming Language :: Python :: 3.9
Classifier: Programming Language :: Python :: 3.10
Classifier: Topic :: Utilities
Requires-Python: >=3.7
License-File: LICENSE.md
Requires-Dist: beautifulsoup4 (==4.11.1)
Requires-Dist: peewee (==3.15.0)
Requires-Dist: requests (==2.28.0)
